README.rst
setup.cfg
setup.py
knowledgeowl/__init__.py
knowledgeowl.egg-info/PKG-INFO
knowledgeowl.egg-info/SOURCES.txt
knowledgeowl.egg-info/dependency_links.txt
knowledgeowl.egg-info/requires.txt
knowledgeowl.egg-info/top_level.txt