Metadata-Version: 1.1
Name: knowledgeowl
Version: 0.0.2
Summary: Library for accessing KnowledgeOwl
Home-page: https://github.com/blade2005/knowledgeowl
Author: Craig Davis
Author-email: UNKNOWN
License: GPLv3
Keywords: knowledgeowl
Platform: UNKNOWN
Classifier: Development Status :: 3 - Alpha
Classifier: Intended Audience :: Developers
Classifier: Topic :: Software Development :: Build Tools
Classifier: License :: OSI Approved :: GNU General Public License v3 (GPLv3)
Classifier: Programming Language :: Python :: 2
Classifier: Programming Language :: Python :: 2.7
